rwkv_emb/model.py
rwkv_emb/test.py
rwkv_emb/test_tokenizer.py
rwkv_emb/tokenizer.py
rwkv_emb/reference/__init__.py
rwkv_emb/reference/rwkv7.py
rwkv_emb/reference/rwkv_vocab_v20230424.txt
rwkv_emb/reference/utils.py
rwkv_emb/reference/cuda/rwkv7_state_fwd_fp16.cpp
rwkv_emb/reference/cuda/rwkv7_state_fwd_fp16.cu
rwkv_emb-0.2.6.dist-info/licenses/LICENSE
rwkv_emb-0.2.6.dist-info/METADATA
rwkv_emb-0.2.6.dist-info/WHEEL
rwkv_emb-0.2.6.dist-info/top_level.txt
rwkv_emb-0.2.6.dist-info/RECORD
