Metadata-Version: 2.4
Name: rwkv-emb
Version: 0.2.6
Summary: The EmbeddingRWKV Model
Author: Haowen HOU
Project-URL: Homepage, https://github.com/howard-hou/EmbeddingRWKV
Project-URL: Bug Tracker, https://github.com/howard-hou/EmbeddingRWKV/issues
Classifier: Programming Language :: Python :: 3
Classifier: License :: OSI Approved :: Apache Software License
Classifier: Operating System :: OS Independent
Requires-Python: >=3.7
License-File: LICENSE
Dynamic: license-file
